climdata/__init__.py
climdata/_vendor/__init__.py
climdata/_vendor/imputegap/__init__.py
climdata/_vendor/imputegap/runner_benchmark.py
climdata/_vendor/imputegap/runner_contamination.py
climdata/_vendor/imputegap/runner_display.py
climdata/_vendor/imputegap/runner_downstream.py
climdata/_vendor/imputegap/runner_explainer.py
climdata/_vendor/imputegap/runner_features.py
climdata/_vendor/imputegap/runner_imputation.py
climdata/_vendor/imputegap/runner_loading.py
climdata/_vendor/imputegap/runner_optimization.py
climdata/_vendor/imputegap/algorithms/__init__.py
climdata/_vendor/imputegap/algorithms/bayotide.py
climdata/_vendor/imputegap/algorithms/bit_graph.py
climdata/_vendor/imputegap/algorithms/brits.py
climdata/_vendor/imputegap/algorithms/cdrec.py
climdata/_vendor/imputegap/algorithms/cpp_integration.py
climdata/_vendor/imputegap/algorithms/deep_mvi.py
climdata/_vendor/imputegap/algorithms/dynammo.py
climdata/_vendor/imputegap/algorithms/gain.py
climdata/_vendor/imputegap/algorithms/gpt4ts.py
climdata/_vendor/imputegap/algorithms/grin.py
climdata/_vendor/imputegap/algorithms/grouse.py
climdata/_vendor/imputegap/algorithms/hkmf_t.py
climdata/_vendor/imputegap/algorithms/iim.py
climdata/_vendor/imputegap/algorithms/interpolation.py
climdata/_vendor/imputegap/algorithms/iterative_svd.py
climdata/_vendor/imputegap/algorithms/knn.py
climdata/_vendor/imputegap/algorithms/mean_impute.py
climdata/_vendor/imputegap/algorithms/mean_impute_by_series.py
climdata/_vendor/imputegap/algorithms/mice.py
climdata/_vendor/imputegap/algorithms/min_impute.py
climdata/_vendor/imputegap/algorithms/miss_forest.py
climdata/_vendor/imputegap/algorithms/miss_net.py
climdata/_vendor/imputegap/algorithms/mpin.py
climdata/_vendor/imputegap/algorithms/mrnn.py
climdata/_vendor/imputegap/algorithms/nuwats.py
climdata/_vendor/imputegap/algorithms/pristi.py
climdata/_vendor/imputegap/algorithms/rosl.py
climdata/_vendor/imputegap/algorithms/soft_impute.py
climdata-0.5.0.dist-info/licenses/LICENSE
climdata-0.5.0.dist-info/METADATA
climdata-0.5.0.dist-info/WHEEL
climdata-0.5.0.dist-info/entry_points.txt
climdata-0.5.0.dist-info/top_level.txt
climdata-0.5.0.dist-info/RECORD
