Metadata-Version: 2.4
Name: climdata
Version: 0.5.0
Summary: This project automates the fetching and extraction of weather data from multiple sources — such as MSWX, DWD HYRAS, ERA5-Land, NASA-NEX-GDDP, and more — for a given location and time range.
Author-email: Kaushik Muduchuru <kaushik.reddy.m@gmail.com>
License: MIT License
Project-URL: Homepage, https://github.com/Kaushikreddym/climdata
Keywords: climdata
Classifier: Intended Audience :: Developers
Classifier: License :: OSI Approved :: MIT License
Classifier: Natural Language :: English
Classifier: Programming Language :: Python :: 3.8
Classifier: Programming Language :: Python :: 3.9
Classifier: Programming Language :: Python :: 3.10
Classifier: Programming Language :: Python :: 3.11
Classifier: Programming Language :: Python :: 3.12
Requires-Python: >=3.8
License-File: LICENSE
Requires-Dist: openpyxl
Requires-Dist: pandas
Requires-Dist: geopandas
Requires-Dist: rioxarray
Requires-Dist: dask[complete]
Requires-Dist: cartopy
Requires-Dist: colormaps
Requires-Dist: matplotlib
Requires-Dist: scipy
Requires-Dist: pymannkendall
Requires-Dist: tqdm
Requires-Dist: zarr
Requires-Dist: wetterdienst
Requires-Dist: pint-pandas
Requires-Dist: cdsapi
Requires-Dist: isimip-client
Requires-Dist: hydra-core
Requires-Dist: aiohttp
Requires-Dist: requests
Requires-Dist: gcsfs
Requires-Dist: dask-jobqueue
Requires-Dist: seaborn
Requires-Dist: earthengine-api
Requires-Dist: geemap
Requires-Dist: xarray
Requires-Dist: xesmf
Requires-Dist: intake
Requires-Dist: intake-esm
Requires-Dist: xsdba
Requires-Dist: xclim
Requires-Dist: pyarrow
Requires-Dist: fastparquet
Requires-Dist: mlflow
Requires-Dist: scikit-learn
Requires-Dist: xgboost
Requires-Dist: optuna
Requires-Dist: gitpython
Requires-Dist: beautifulsoup4
Requires-Dist: google-auth
Requires-Dist: google-api-python-client
Requires-Dist: toml
Requires-Dist: shap
Requires-Dist: pycatch22
Requires-Dist: scikit-optimize
Requires-Dist: pyswarms
Requires-Dist: pytest
Requires-Dist: xlsxwriter
Requires-Dist: types-toml
Requires-Dist: types-setuptools
Requires-Dist: wheel
Requires-Dist: statsmodels
Requires-Dist: plotly
Requires-Dist: ujson
Requires-Dist: ipdb
Requires-Dist: tables
Requires-Dist: MissForest
Requires-Dist: lightgbm
Requires-Dist: einops
Requires-Dist: ray
Requires-Dist: fire
Requires-Dist: fastdtw
Requires-Dist: pyqt5
Provides-Extra: all
Requires-Dist: pandas; extra == "all"
Provides-Extra: extra
Requires-Dist: pandas; extra == "extra"
Dynamic: license-file
